pyCRC_plot/CRC.py
pyCRC_plot/__init__.py
pyCRC_plot/gui.py
pyCRC_plot/show_results.py
pyCRC_plot-0.1.5.dist-info/LICENSE
pyCRC_plot-0.1.5.dist-info/METADATA
pyCRC_plot-0.1.5.dist-info/WHEEL
pyCRC_plot-0.1.5.dist-info/entry_points.txt
pyCRC_plot-0.1.5.dist-info/top_level.txt
pyCRC_plot-0.1.5.dist-info/RECORD
