Metadata-Version: 2.1
Name: pyCRC-plot
Version: 0.1.5
Summary: Concentration response curve fitting and plotting written in python
Author-email: Franco Viscarra <franco.viscarra@bioch.ox.ac.uk>
License: GNU GENERAL PUBLIC LICENSE
Project-URL: Homepage, https://github.com/francoviscarra/pycrcplot
Project-URL: Bug Tracker, https://github.com/francoviscarra/pycrcplot/issues
Classifier: Programming Language :: Python :: 3
Classifier: Operating System :: OS Independent
Classifier: Intended Audience :: Science/Research
Classifier: Topic :: Scientific/Engineering
Requires-Python: >=3.9
License-File: LICENSE
Requires-Dist: seaborn
Requires-Dist: tksheet
Requires-Dist: matplotlib
Requires-Dist: scipy
Requires-Dist: pandas
Requires-Dist: numpy
Requires-Dist: importlib-metadata ; python_version < "3.8"
